{
    "name": "Magical Ogre",
    "type": "feat",
    "img": "",
    "system": {
        "description": {
            "value": "<p>&nbsp;You know the&nbsp;<em>Friends</em>&nbsp;cantrip. When you reach 3rd level, you can cast&nbsp;<em>Charm Person</em>&nbsp;and regain the ability to do so when you finish a long rest. When you reach 5th level, you can cast the&nbsp;<em>Darkness</em>&nbsp;spell once with this trait and regain the ability to do so when you finish a long rest. Intelligence, Wisdom, or Charisma is your spellcasting ability for these spells.</p>",
            "chat": "",
            "unidentified": ""
        },
        "source": "Core Rules",
        "type": {
            "value": "race"
        }
    },
    "effects": [],
    "folder": null,
    "sort": 0,
    "ownership": {
        "default": 0
    },
    "flags": {},
    "_id": "JBPS2A2QSOWLFCWL"
}